{
  "lectureId": "sf-20",
  "title": "Prostaglandines",
  "category": "Sciences Fondamentales",
  "questions": [
    {
      "id": "q1",
      "type": "quiz",
      "difficulty": "facile",
      "question": "Les prostaglandines appartiennent à quelle grande famille de médiateurs lipidiques ?",
      "options": [
        {
          "id": "A",
          "text": "A. Stéroïdes",
          "correct": false
        },
        {
          "id": "B",
          "text": "B. Eicosanoïdes",
          "correct": true
        },
        {
          "id": "C",
          "text": "C. Phospholipides",
          "correct": false
        },
        {
          "id": "D",
          "text": "D. Glycolipides",
          "correct": false
        },
        {
          "id": "E",
          "text": "E. Sphingolipides",
          "correct": false
        }
      ],
      "explanation": "Les prostaglandines sont des médiateurs lipidiques locaux, appartenant à la grande famille des eicosanoïdes."
    },
    {
      "id": "q2",
      "type": "quiz",
      "difficulty": "facile",
      "question": "Concernant la synthèse et le stockage des prostaglandines, quelle affirmation est exacte ?",
      "options": [
        {
          "id": "A",
          "text": "A. Elles sont stockées dans des vésicules et libérées sur demande.",
          "correct": false
        },
        {
          "id": "B",
          "text": "B. Elles sont synthétisées en permanence et stockées dans le cytoplasme.",
          "correct": false
        },
        {
          "id": "C",
          "text": "C. Elles sont synthétisées à la demande et ne sont pas stockées.",
          "correct": true
        },
        {
          "id": "D",
          "text": "D. Elles sont synthétisées uniquement par les cellules inflammatoires.",
          "correct": false
        },
        {
          "id": "E",
          "text": "E. Elles sont stockées dans la membrane cellulaire.",
          "correct": false
        }
      ],
      "explanation": "Les prostaglandines ne sont pas stockées mais sont synthétisées à la demande par la quasi-totalité des cellules de l'organisme."
    },
    {
      "id": "q3",
      "type": "quiz",
      "difficulty": "facile",
      "question": "Quelle enzyme est responsable de la libération de l'acide arachidonique à partir des phospholipides membranaires ?",
      "options": [
        {
          "id": "A",
          "text": "A. Cyclooxygénase",
          "correct": false
        },
        {
          "id": "B",
          "text": "B. Lipoxygénase",
          "correct": false
        },
        {
          "id": "C",
          "text": "C. Phospholipase A2",
          "correct": true
        },
        {
          "id": "D",
          "text": "D. Thromboxane synthase",
          "correct": false
        },
        {
          "id": "E",
          "text": "E. Prostacycline synthase",
          "correct": false
        }
      ],
      "explanation": "En réponse à un stimulus, la phospholipase A2 (PLA2) est activée et clive les phospholipides de la membrane cellulaire pour libérer l'acide arachidonique."
    },
    {
      "id": "q4",
      "type": "quiz",
      "difficulty": "facile",
      "question": "Quel est le substrat direct des cyclooxygénases (COX) dans la voie de synthèse des prostaglandines ?",
      "options": [
        {
          "id": "A",
          "text": "A. Phospholipides membranaires",
          "correct": false
        },
        {
          "id": "B",
          "text": "B. Prostaglandine H2 (PGH2)",
          "correct": false
        },
        {
          "id": "C",
          "text": "C. Acide arachidonique",
          "correct": true
        },
        {
          "id": "D",
          "text": "D. Thromboxane A2 (TXA2)",
          "correct": false
        },
        {
          "id": "E",
          "text": "E. Prostacycline (PGI2)",
          "correct": false
        }
      ],
      "explanation": "L'acide arachidonique est le substrat des enzymes clés de la voie, les cyclooxygénases (COX)."
    },
    {
      "id": "q5",
      "type": "quiz",
      "difficulty": "facile",
      "question": "La cyclooxygénase-1 (COX-1) est principalement impliquée dans quelles fonctions ?",
      "options": [
        {
          "id": "A",
          "text": "A. La production de prostaglandines de l'inflammation.",
          "correct": false
        },
        {
          "id": "B",
          "text": "B. Des fonctions physiologiques de maintenance (homéostasie).",
          "correct": true
        },
        {
          "id": "C",
          "text": "C. La réponse aux cytokines inflammatoires.",
          "correct": false
        },
        {
          "id": "D",
          "text": "D. La synthèse de prostaglandines uniquement dans les sites d'inflammation.",
          "correct": false
        },
        {
          "id": "E",
          "text": "E. L'induction de la fièvre.",
          "correct": false
        }
      ],
      "explanation": "La COX-1 est une enzyme constitutive, responsable de la production de prostaglandines impliquées dans des fonctions physiologiques de 'maintenance' (homéostasie)."
    },
    {
      "id": "q6",
      "type": "quiz",
      "difficulty": "intermediaire",
      "question": "Quels sont les effets des glucocorticoïdes sur la synthèse des prostaglandines ?",
      "options": [
        {
          "id": "A",
          "text": "A. Ils activent la cyclooxygénase.",
          "correct": false
        },
        {
          "id": "B",
          "text": "B. Ils inhibent la phospholipase A2.",
          "correct": true
        },
        {
          "id": "C",
          "text": "C. Ils augmentent la production d'acide arachidonique.",
          "correct": false
        },
        {
          "id": "D",
          "text": "D. Ils stimulent la synthèse de PGH2.",
          "correct": false
        },
        {
          "id": "E",
          "text": "E. Ils inhibent les synthases spécifiques de prostaglandines.",
          "correct": false
        }
      ],
      "explanation": "La libération de l'acide arachidonique par la phospholipase A2 est inhibée par les glucocorticoïdes, ce qui explique une partie de leur puissant effet anti-inflammatoire."
    },
    {
      "id": "q7",
      "type": "quiz",
      "difficulty": "intermediaire",
      "question": "L'acide arachidonique est caractérisé par :",
      "options": [
        {
          "id": "A",
          "text": "A. Être un acide gras saturé.",
          "correct": false
        },
        {
          "id": "B",
          "text": "B. Posséder 18 atomes de carbone.",
          "correct": false
        },
        {
          "id": "C",
          "text": "C. Être un acide gras polyinsaturé.",
          "correct": true
        },
        {
          "id": "D",
          "text": "D. Posséder 20 atomes de carbone.",
          "correct": true
        },
        {
          "id": "E",
          "text": "E. Être directement synthétisé par la COX.",
          "correct": false
        }
      ],
      "explanation": "L'acide arachidonique est un acide gras polyinsaturé à 20 atomes de carbone."
    },
    {
      "id": "q8",
      "type": "quiz",
      "difficulty": "intermediaire",
      "question": "L'expression de la cyclooxygénase-2 (COX-2) est massivement induite par :",
      "options": [
        {
          "id": "A",
          "text": "A. Les glucocorticoïdes.",
          "correct": false
        },
        {
          "id": "B",
          "text": "B. Les phospholipides membranaires.",
          "correct": false
        },
        {
          "id": "C",
          "text": "C. Des cytokines telles que le TNF et l'IL-1.",
          "correct": true
        },
        {
          "id": "D",
          "text": "D. L'acide arachidonique.",
          "correct": false
        },
        {
          "id": "E",
          "text": "E. La prostaglandine H2.",
          "correct": false
        }
      ],
      "explanation": "La COX-2 est une enzyme inductible dont l'expression est massivement induite dans les sites d'inflammation par des cytokines (TNF, IL-1)."
    },
    {
      "id": "q9",
      "type": "quiz",
      "difficulty": "intermediaire",
      "question": "La prostaglandine H2 (PGH2) est un intermédiaire instable qui peut être converti en quelles prostaglandines biologiquement actives ?",
      "options": [
        {
          "id": "A",
          "text": "A. Prostacycline (PGI2)",
          "correct": true
        },
        {
          "id": "B",
          "text": "B. Thromboxane A2 (TXA2)",
          "correct": true
        },
        {
          "id": "C",
          "text": "C. Prostaglandine D2 (PGD2)",
          "correct": true
        },
        {
          "id": "D",
          "text": "D. Prostaglandine E2 (PGE2)",
          "correct": true
        },
        {
          "id": "E",
          "text": "E. Acide arachidonique",
          "correct": false
        }
      ],
      "explanation": "La PGH2 est ensuite convertie en différentes prostaglandines biologiquement actives par des synthases spécifiques, notamment la Prostacycline (PGI2), le Thromboxane A2 (TXA2), la Prostaglandine D2 (PGD2) et la Prostaglandine E2 (PGE2)."
    },
    {
      "id": "q10",
      "type": "quiz",
      "difficulty": "intermediaire",
      "question": "Dans le contexte de l'inflammation, quels sont les effets des PGE2 et PGI2 ?",
      "options": [
        {
          "id": "A",
          "text": "A. Vasoconstriction.",
          "correct": false
        },
        {
          "id": "B",
          "text": "B. Diminution de la perméabilité vasculaire.",
          "correct": false
        },
        {
          "id": "C",
          "text": "C. Vasodilatation.",
          "correct": true
        },
        {
          "id": "D",
          "text": "D. Augmentation de la perméabilité vasculaire.",
          "correct": true
        },
        {
          "id": "E",
          "text": "E. Inhibition des effets de l'histamine.",
          "correct": false
        }
      ],
      "explanation": "Les PGE2 et PGI2 sont de puissants vasodilatateurs et augmentent la perméabilité vasculaire, contribuant à la rougeur et à l'œdème."
    },
    {
      "id": "q11",
      "type": "quiz",
      "difficulty": "intermediaire",
      "question": "Quel est le rôle des prostaglandines dans la douleur ?",
      "options": [
        {
          "id": "A",
          "text": "A. Elles provoquent directement la douleur.",
          "correct": false
        },
        {
          "id": "B",
          "text": "B. Elles sensibilisent les terminaisons nerveuses nociceptives.",
          "correct": true
        },
        {
          "id": "C",
          "text": "C. Elles inhibent l'action des médiateurs algogènes.",
          "correct": false
        },
        {
          "id": "D",
          "text": "D. Elles agissent comme des analgésiques directs.",
          "correct": false
        },
        {
          "id": "E",
          "text": "E. Elles potentialisent l'action de la bradykinine et de l'histamine sur les nocicepteurs.",
          "correct": true
        }
      ],
      "explanation": "Les prostaglandines ne provoquent pas directement la douleur mais sensibilisent les terminaisons nerveuses nociceptives à l'action d'autres médiateurs algogènes (bradykinine, histamine)."
    },
    {
      "id": "q12",
      "type": "quiz",
      "difficulty": "intermediaire",
      "question": "Comment les prostaglandines contribuent-elles à la fièvre ?",
      "options": [
        {
          "id": "A",
          "text": "A. Elles inhibent la production d'IL-1.",
          "correct": false
        },
        {
          "id": "B",
          "text": "B. Elles agissent directement sur les muscles pour augmenter la température.",
          "correct": false
        },
        {
          "id": "C",
          "text": "C. La PGE2 est produite dans l'hypothalamus en réponse à des cytokines.",
          "correct": true
        },
        {
          "id": "D",
          "text": "D. La PGE2 élève le 'point de consigne' du centre thermorégulateur.",
          "correct": true
        },
        {
          "id": "E",
          "text": "E. Elles diminuent la température corporelle.",
          "correct": false
        }
      ],
      "explanation": "Lors d'une infection, des cytokines comme l'IL-1 stimulent la production de PGE2 dans l'hypothalamus. La PGE2 agit sur le centre thermorégulateur pour élever le 'point de consigne' de la température corporelle, provoquant la fièvre."
    },
    {
      "id": "q13",
      "type": "quiz",
      "difficulty": "intermediaire",
      "question": "Parmi les rôles physiologiques suivants, lesquels sont principalement liés à l'activité de la COX-1 ?",
      "options": [
        {
          "id": "A",
          "text": "A. Protection de la muqueuse gastrique.",
          "correct": true
        },
        {
          "id": "B",
          "text": "B. Vasodilatation dans l'inflammation.",
          "correct": false
        },
        {
          "id": "C",
          "text": "C. Fonction rénale (maintien du flux sanguin).",
          "correct": true
        },
        {
          "id": "D",
          "text": "D. Agrégation plaquettaire via TXA2.",
          "correct": true
        },
        {
          "id": "E",
          "text": "E. Fièvre.",
          "correct": false
        }
      ],
      "explanation": "Les rôles physiologiques principalement liés à la COX-1 incluent la protection de la muqueuse gastrique, le maintien de la fonction rénale et l'hémostase via le Thromboxane A2 (TXA2) produit par les plaquettes (via la COX-1)."
    },
    {
      "id": "q14",
      "type": "quiz",
      "difficulty": "intermediaire",
      "question": "Comment les prostaglandines protègent-elles la muqueuse gastrique ?",
      "options": [
        {
          "id": "A",
          "text": "A. En augmentant la sécrétion d'acide gastrique.",
          "correct": false
        },
        {
          "id": "B",
          "text": "B. En diminuant la sécrétion de mucus protecteur.",
          "correct": false
        },
        {
          "id": "C",
          "text": "C. En stimulant la sécrétion de bicarbonate.",
          "correct": true
        },
        {
          "id": "D",
          "text": "D. En diminuant la secretion d'acide gastrique.",
          "correct": true
        },
        {
          "id": "E",
          "text": "E. En stimulant la sécrétion de mucus protecteur.",
          "correct": true
        }
      ],
      "explanation": "Les prostaglandines stimulent la sécrétion de mucus protecteur et de bicarbonate, et diminuent la sécrétion d'acide gastrique."
    },
    {
      "id": "q15",
      "type": "quiz",
      "difficulty": "intermediaire",
      "question": "Quel est le rôle des prostaglandines dans la fonction rénale ?",
      "options": [
        {
          "id": "A",
          "text": "A. Elles provoquent la vasoconstriction de l'artériole afférente.",
          "correct": false
        },
        {
          "id": "B",
          "text": "B. Elles maintiennent la vasodilatation de l'artériole afférente.",
          "correct": true
        },
        {
          "id": "C",
          "text": "C. Elles diminuent le flux sanguin rénal.",
          "correct": false
        },
        {
          "id": "D",
          "text": "D. Elles sont essentielles pour un flux sanguin rénal adéquat, surtout en cas de bas débit.",
          "correct": true
        },
        {
          "id": "E",
          "text": "E. Elles augmentent la réabsorption de sodium.",
          "correct": false
        }
      ],
      "explanation": "Les prostaglandines maintiennent la vasodilatation de l'artériole afférente du glomérule, assurant un flux sanguin rénal adéquat, surtout en cas de bas débit."
    },
    {
      "id": "q16",
      "type": "quiz",
      "difficulty": "intermediaire",
      "question": "Le Thromboxane A2 (TXA2) est caractérisé par :",
      "options": [
        {
          "id": "A",
          "text": "A. Être produit par les cellules endothéliales.",
          "correct": false
        },
        {
          "id": "B",
          "text": "B. Être un puissant anti-agrégant plaquettaire.",
          "correct": false
        },
        {
          "id": "C",
          "text": "C. Être un puissant pro-agrégant plaquettaire.",
          "correct": true
        },
        {
          "id": "D",
          "text": "D. Être un vasoconstricteur.",
          "correct": true
        },
        {
          "id": "E",
          "text": "E. Sa production est médiée par la COX-2.",
          "correct": false
        }
      ],
      "explanation": "Le Thromboxane A2 (TXA2), produit par les plaquettes (via la COX-1), est un puissant pro-agrégant plaquettaire et vasoconstricteur."
    },
    {
      "id": "q17",
      "type": "quiz",
      "difficulty": "intermediaire",
      "question": "La Prostacycline (PGI2) est caractérisée par :",
      "options": [
        {
          "id": "A",
          "text": "A. Être produite par les plaquettes.",
          "correct": false
        },
        {
          "id": "B",
          "text": "B. Être un puissant anti-agrégant plaquettaire.",
          "correct": true
        },
        {
          "id": "C",
          "text": "C. Être un vasoconstricteur.",
          "correct": false
        },
        {
          "id": "D",
          "text": "D. Être un vasodilatateur.",
          "correct": true
        },
        {
          "id": "E",
          "text": "E. Sa production est médiée par la COX-1.",
          "correct": false
        }
      ],
      "explanation": "La Prostacycline (PGI2), produite par les cellules endothéliales (via la COX-2), est un puissant anti-agrégant plaquettaire et vasodilatateur."
    },
    {
      "id": "q18",
      "type": "quiz",
      "difficulty": "intermediaire",
      "question": "Quel est le rôle des prostaglandines (PGE2, PGF2a) au niveau de l'utérus ?",
      "options": [
        {
          "id": "A",
          "text": "A. Relaxation du myomètre.",
          "correct": false
        },
        {
          "id": "B",
          "text": "B. Inhibition du déclenchement du travail.",
          "correct": false
        },
        {
          "id": "C",
          "text": "C. Contraction du myomètre.",
          "correct": true
        },
        {
          "id": "D",
          "text": "D. Rôle dans les dysménorrhées.",
          "correct": true
        },
        {
          "id": "E",
          "text": "E. Diminution de la sensibilité utérine.",
          "correct": false
        }
      ],
      "explanation": "Les prostaglandines (PGE2, PGF2a) provoquent la contraction du myomètre (rôle dans le déclenchement du travail et dans les dysménorrhées)."
    },
    {
      "id": "q19",
      "type": "quiz",
      "difficulty": "intermediaire",
      "question": "Les Anti-Inflammatoires Non Stéroïdiens (AINS) exercent quels effets thérapeutiques ?",
      "options": [
        {
          "id": "A",
          "text": "A. Anti-inflammatoire.",
          "correct": true
        },
        {
          "id": "B",
          "text": "B. Antalgique.",
          "correct": true
        },
        {
          "id": "C",
          "text": "C. Antipyrétique.",
          "correct": true
        },
        {
          "id": "D",
          "text": "D. Pro-agrégant plaquettaire.",
          "correct": false
        },
        {
          "id": "E",
          "text": "E. Vasoconstricteur rénal.",
          "correct": false
        }
      ],
      "explanation": "Les AINS exercent leurs effets thérapeutiques (anti-inflammatoire, antalgique, antipyrétique) en inhibant les enzymes COX."
    },
    {
      "id": "q20",
      "type": "quiz",
      "difficulty": "intermediaire",
      "question": "Quel est le mécanisme d'action général des AINS ?",
      "options": [
        {
          "id": "A",
          "text": "A. Activation de la phospholipase A2.",
          "correct": false
        },
        {
          "id": "B",
          "text": "B. Inhibition des enzymes cyclooxygénases (COX).",
          "correct": true
        },
        {
          "id": "C",
          "text": "C. Stimulation de la production de prostaglandines.",
          "correct": false
        },
        {
          "id": "D",
          "text": "D. Blocage des récepteurs aux prostaglandines.",
          "correct": false
        },
        {
          "id": "E",
          "text": "E. Inhibition de la synthèse d'acide arachidonique.",
          "correct": false
        }
      ],
      "explanation": "Les AINS exercent leurs effets en inhibant les enzymes COX, bloquant ainsi la production de toutes les prostaglandines."
    },
    {
      "id": "q21",
      "type": "quiz",
      "difficulty": "intermediaire",
      "question": "Les AINS classiques (non-sélectifs) inhibent :",
      "options": [
        {
          "id": "A",
          "text": "A. Uniquement la COX-1.",
          "correct": false
        },
        {
          "id": "B",
          "text": "B. Uniquement la COX-2.",
          "correct": false
        },
        {
          "id": "C",
          "text": "C. À la fois la COX-1 et la COX-2.",
          "correct": true
        },
        {
          "id": "D",
          "text": "D. La phospholipase A2.",
          "correct": false
        },
        {
          "id": "E",
          "text": "E. Les synthases spécifiques de prostaglandines.",
          "correct": false
        }
      ],
      "explanation": "Les AINS classiques (non-sélectifs) inhibent à la fois la COX-1 et la COX-2."
    },
    {
      "id": "q22",
      "type": "quiz",
      "difficulty": "intermediaire",
      "question": "L'effet thérapeutique anti-inflammatoire des AINS classiques est principalement dû à l'inhibition de :",
      "options": [
        {
          "id": "A",
          "text": "A. La phospholipase A2.",
          "correct": false
        },
        {
          "id": "B",
          "text": "B. La COX-1.",
          "correct": false
        },
        {
          "id": "C",
          "text": "C. La COX-2.",
          "correct": true
        },
        {
          "id": "D",
          "text": "D. La thromboxane synthase.",
          "correct": false
        },
        {
          "id": "E",
          "text": "E. La prostacycline synthase.",
          "correct": false
        }
      ],
      "explanation": "L'inhibition de la COX-2 est responsable des effets thérapeutiques (anti-inflammatoires) des AINS classiques."
    },
    {
      "id": "q23",
      "type": "quiz",
      "difficulty": "intermediaire",
      "question": "Quels sont les principaux effets secondaires des AINS classiques ?",
      "options": [
        {
          "id": "A",
          "text": "A. Toxicité gastrique.",
          "correct": true
        },
        {
          "id": "B",
          "text": "B. Toxicité rénale.",
          "correct": true
        },
        {
          "id": "C",
          "text": "C. Effet pro-agrégant plaquettaire.",
          "correct": false
        },
        {
          "id": "D",
          "text": "D. Augmentation de la protection de la muqueuse gastrique.",
          "correct": false
        },
        {
          "id": "E",
          "text": "E. Vasodilatation de l'artériole afférente rénale.",
          "correct": false
        }
      ],
      "explanation": "L'inhibition de la COX-1 par les AINS classiques est responsable de la plupart des effets secondaires, notamment la toxicité gastrique et la toxicité rénale."
    },
    {
      "id": "q24",
      "type": "quiz",
      "difficulty": "intermediaire",
      "question": "La toxicité gastrique des AINS classiques se manifeste par :",
      "options": [
        {
          "id": "A",
          "text": "A. Une augmentation de la sécrétion de mucus.",
          "correct": false
        },
        {
          "id": "B",
          "text": "B. Une suppression de la protection de la muqueuse.",
          "correct": true
        },
        {
          "id": "C",
          "text": "C. Des ulcères.",
          "correct": true
        },
        {
          "id": "D",
          "text": "D. Des saignements digestifs.",
          "correct": true
        },
        {
          "id": "E",
          "text": "E. Une augmentation de la sécrétion de bicarbonate.",
          "correct": false
        }
      ],
      "explanation": "La toxicité gastrique des AINS classiques se traduit par des ulcères et des saignements digestifs par suppression de la protection de la muqueuse."
    },
    {
      "id": "q25",
      "type": "quiz",
      "difficulty": "intermediaire",
      "question": "La toxicité rénale des AINS classiques est due à :",
      "options": [
        {
          "id": "A",
          "text": "A. Une vasodilatation de l'artériole afférente.",
          "correct": false
        },
        {
          "id": "B",
          "text": "B. Une vasoconstriction de l'artériole afférente.",
          "correct": true
        },
        {
          "id": "C",
          "text": "C. Une augmentation du flux sanguin rénal.",
          "correct": false
        },
        {
          "id": "D",
          "text": "D. Une insuffisance rénale aiguë fonctionnelle.",
          "correct": true
        },
        {
          "id": "E",
          "text": "E. Une stimulation de la production de prostaglandines rénales.",
          "correct": false
        }
      ],
      "explanation": "La toxicité rénale des AINS classiques est une insuffisance rénale aiguë fonctionnelle par vasoconstriction de l'artériole afférente."
    },
    {
      "id": "q26",
      "type": "quiz",
      "difficulty": "difficile",
      "question": "Quelles sont les caractéristiques distinctives de la COX-1 et de la COX-2 ?",
      "options": [
        {
          "id": "A",
          "text": "A. La COX-1 est inductible, la COX-2 est constitutive.",
          "correct": false
        },
        {
          "id": "B",
          "text": "B. La COX-1 est exprimée en permanence, la COX-2 est normalement faible mais induite.",
          "correct": true
        },
        {
          "id": "C",
          "text": "C. La COX-1 produit des PG de l'inflammation, la COX-2 des PG physiologiques.",
          "correct": false
        },
        {
          "id": "D",
          "text": "D. La COX-1 est responsable de l'homéostasie, la COX-2 de l'inflammation.",
          "correct": true
        },
        {
          "id": "E",
          "text": "E. La COX-1 est inhibée par les cytokines, la COX-2 par les glucocorticoïdes.",
          "correct": false
        }
      ],
      "explanation": "La COX-1 est une enzyme constitutive, exprimée en permanence et responsable des fonctions physiologiques de maintenance (homéostasie). La COX-2 est une enzyme inductible, dont l'expression est normalement faible mais massivement induite dans les sites d'inflammation, et est principalement responsable de la production des prostaglandines de l'inflammation."
    },
    {
      "id": "q27",
      "type": "quiz",
      "difficulty": "difficile",
      "question": "Concernant le mode d'action et la demi-vie des prostaglandines, quelles affirmations sont exactes ?",
      "options": [
        {
          "id": "A",
          "text": "A. Elles agissent principalement de manière endocrine.",
          "correct": false
        },
        {
          "id": "B",
          "text": "B. Elles ont une demi-vie très courte.",
          "correct": true
        },
        {
          "id": "C",
          "text": "C. Elles agissent de manière autocrine.",
          "correct": true
        },
        {
          "id": "D",
          "text": "D. Elles agissent de manière paracrine.",
          "correct": true
        },
        {
          "id": "E",
          "text": "E. Leurs effets biologiques sont toujours identiques quel que soit le récepteur.",
          "correct": false
        }
      ],
      "explanation": "Les prostaglandines agissent de manière autocrine (sur la cellule qui les produit) ou paracrine (sur les cellules voisines) et ont une demi-vie très courte. Leurs effets biologiques sont extrêmement variés et parfois opposés selon le type de prostaglandine et le récepteur."
    },
    {
      "id": "q28",
      "type": "quiz",
      "difficulty": "difficile",
      "question": "La diversité des effets biologiques des prostaglandines s'explique par :",
      "options": [
        {
          "id": "A",
          "text": "A. Leur synthèse à partir de différents acides gras.",
          "correct": false
        },
        {
          "id": "B",
          "text": "B. L'action de synthases spécifiques exprimées de manière tissu-spécifique.",
          "correct": true
        },
        {
          "id": "C",
          "text": "C. La conversion de PGH2 en différentes prostaglandines actives.",
          "correct": true
        },
        {
          "id": "D",
          "text": "D. Leur action sur un seul type de récepteur.",
          "correct": false
        },
        {
          "id": "E",
          "text": "E. Leur longue demi-vie.",
          "correct": false
        }
      ],
      "explanation": "La PGH2 est convertie en différentes prostaglandines biologiquement actives par des synthases spécifiques, qui sont exprimées de manière tissu-spécifique. Cela explique la diversité des effets des prostaglandines."
    },
    {
      "id": "q29",
      "type": "quiz",
      "difficulty": "difficile",
      "question": "La prostaglandine H2 (PGH2) est un intermédiaire clé car elle est :",
      "options": [
        {
          "id": "A",
          "text": "A. Le produit final de la phospholipase A2.",
          "correct": false
        },
        {
          "id": "B",
          "text": "B. Le substrat direct de la cyclooxygénase.",
          "correct": false
        },
        {
          "id": "C",
          "text": "C. Un intermédiaire instable.",
          "correct": true
        },
        {
          "id": "D",
          "text": "D. Convertie en différentes prostaglandines biologiquement actives.",
          "correct": true
        },
        {
          "id": "E",
          "text": "E. La seule prostaglandine avec des effets physiologiques.",
          "correct": false
        }
      ],
      "explanation": "La COX catalyse la transformation de l'acide arachidonique en un intermédiaire instable, la prostaglandine H2 (PGH2), qui est ensuite convertie en différentes prostaglandines biologiquement actives par des synthases spécifiques."
    },
    {
      "id": "q30",
      "type": "quiz",
      "difficulty": "difficile",
      "question": "Dans le processus inflammatoire, les PGE2 et PGI2 potentialisent les effets de quels autres médiateurs ?",
      "options": [
        {
          "id": "A",
          "text": "A. Bradykinine.",
          "correct": false
        },
        {
          "id": "B",
          "text": "B. Histamine.",
          "correct": true
        },
        {
          "id": "C",
          "text": "C. TNF.",
          "correct": false
        },
        {
          "id": "D",
          "text": "D. IL-1.",
          "correct": false
        },
        {
          "id": "E",
          "text": "E. Acide arachidonique.",
          "correct": false
        }
      ],
      "explanation": "Les PGE2 et PGI2 potentialisent les effets d'autres médiateurs comme l'histamine dans le processus inflammatoire."
    },
    {
      "id": "q31",
      "type": "quiz",
      "difficulty": "difficile",
      "question": "Lors d'une infection, quelle cytokine est mentionnée comme stimulant la production de PGE2 dans l'hypothalamus pour provoquer la fièvre ?",
      "options": [
        {
          "id": "A",
          "text": "A. TNF.",
          "correct": false
        },
        {
          "id": "B",
          "text": "B. IL-6.",
          "correct": false
        },
        {
          "id": "C",
          "text": "C. IL-1.",
          "correct": true
        },
        {
          "id": "D",
          "text": "D. IFN-gamma.",
          "correct": false
        },
        {
          "id": "E",
          "text": "E. IL-10.",
          "correct": false
        }
      ],
      "explanation": "Lors d'une infection, des cytokines comme l'IL-1 stimulent la production de PGE2 dans l'hypothalamus, ce qui provoque la fièvre."
    },
    {
      "id": "q32",
      "type": "quiz",
      "difficulty": "difficile",
      "question": "L'équilibre de l'hémostase impliquant les prostaglandines est maintenu entre :",
      "options": [
        {
          "id": "A",
          "text": "A. Le TXA2 produit par les cellules endothéliales et la PGI2 produite par les plaquettes.",
          "correct": false
        },
        {
          "id": "B",
          "text": "B. Le TXA2 (pro-agrégant) et la PGI2 (anti-agrégant).",
          "correct": true
        },
        {
          "id": "C",
          "text": "C. Le TXA2 (vasoconstricteur) et la PGI2 (vasodilatateur).",
          "correct": true
        },
        {
          "id": "D",
          "text": "D. Le TXA2 produit via COX-1 et la PGI2 produite via COX-2.",
          "correct": true
        },
        {
          "id": "E",
          "text": "E. Le TXA2 et la PGE2.",
          "correct": false
        }
      ],
      "explanation": "Il existe un équilibre entre le Thromboxane A2 (TXA2), produit par les plaquettes (via la COX-1), qui est un puissant pro-agrégant plaquettaire et vasoconstricteur, et la Prostacycline (PGI2), produite par les cellules endothéliales (via la COX-2), qui est un puissant anti-agrégant plaquettaire et vasodilatateur."
    },
    {
      "id": "q33",
      "type": "quiz",
      "difficulty": "difficile",
      "question": "L'aspirine à faible dose a un effet anti-agrégant plaquettaire spécifique. Quelles sont ses caractéristiques ?",
      "options": [
        {
          "id": "A",
          "text": "A. Elle inhibe de manière réversible la COX-1 plaquettaire.",
          "correct": false
        },
        {
          "id": "B",
          "text": "B. Elle inhibe de manière irréversible la COX-1 plaquettaire.",
          "correct": true
        },
        {
          "id": "C",
          "text": "C. Elle bloque la production de TXA2.",
          "correct": true
        },
        {
          "id": "D",
          "text": "D. Elle stimule la production de PGI2.",
          "correct": false
        },
        {
          "id": "E",
          "text": "E. Elle est utilisée en prévention cardiovasculaire.",
          "correct": true
        }
      ],
      "explanation": "L'aspirine à faible dose inhibe de manière irréversible la COX-1 plaquettaire, bloquant la production de TXA2, ce qui est utilisé en prévention cardiovasculaire."
    },
    {
      "id": "q34",
      "type": "quiz",
      "difficulty": "difficile",
      "question": "L'utilisation de l'aspirine à faible dose en prévention cardiovasculaire est justifiée par :",
      "options": [
        {
          "id": "A",
          "text": "A. Son effet anti-inflammatoire puissant.",
          "correct": false
        },
        {
          "id": "B",
          "text": "B. Son inhibition irréversible de la COX-1 plaquettaire.",
          "correct": true
        },
        {
          "id": "C",
          "text": "C. Le blocage de la production de TXA2.",
          "correct": true
        },
        {
          "id": "D",
          "text": "D. La stimulation de la production de PGI2.",
          "correct": false
        },
        {
          "id": "E",
          "text": "E. Son effet vasodilatateur systémique.",
          "correct": false
        }
      ],
      "explanation": "L'aspirine à faible dose inhibe de manière irréversible la COX-1 plaquettaire, bloquant la production de TXA2, ce qui est utilisé en prévention cardiovasculaire."
    },
    {
      "id": "q35",
      "type": "quiz",
      "difficulty": "difficile",
      "question": "Quel était l'objectif principal du développement des AINS sélectifs de la COX-2 (Coxibs) ?",
      "options": [
        {
          "id": "A",
          "text": "A. Augmenter les effets anti-inflammatoires.",
          "correct": false
        },
        {
          "id": "B",
          "text": "B. Réduire la toxicité gastro-intestinale.",
          "correct": true
        },
        {
          "id": "C",
          "text": "C. Épargner la COX-2.",
          "correct": false
        },
        {
          "id": "D",
          "text": "D. Augmenter le risque cardiovasculaire.",
          "correct": false
        },
        {
          "id": "E",
          "text": "E. Inhiber la phospholipase A2.",
          "correct": false
        }
      ],
      "explanation": "Les Coxibs ont été développés pour inhiber préférentiellement la COX-2, en épargnant la COX-1, dans le but de réduire la toxicité gastro-intestinale."
    },
    {
      "id": "q36",
      "type": "quiz",
      "difficulty": "difficile",
      "question": "Les Coxibs agissent en :",
      "options": [
        {
          "id": "A",
          "text": "A. Inhibant préférentiellement la COX-1.",
          "correct": false
        },
        {
          "id": "B",
          "text": "B. Inhibant préférentiellement la COX-2.",
          "correct": true
        },
        {
          "id": "C",
          "text": "C. Bloquant la production de TXA2.",
          "correct": false
        },
        {
          "id": "D",
          "text": "D. Stimulant la production de PGI2.",
          "correct": false
        },
        {
          "id": "E",
          "text": "E. Inhibant à la fois COX-1 et COX-2 de manière égale.",
          "correct": false
        }
      ],
      "explanation": "Les Coxibs ont été développés pour inhiber préférentiellement la COX-2, en épargnant la COX-1."
    },
    {
      "id": "q37",
      "type": "quiz",
      "difficulty": "difficile",
      "question": "Quels sont les risques associés à l'utilisation des AINS sélectifs de la COX-2 (Coxibs) ?",
      "options": [
        {
          "id": "A",
          "text": "A. Réduction significative de la toxicité gastrique.",
          "correct": false
        },
        {
          "id": "B",
          "text": "B. Augmentation du risque d'événements cardiovasculaires.",
          "correct": true
        },
        {
          "id": "C",
          "text": "C. Diminution du risque d'infarctus.",
          "correct": false
        },
        {
          "id": "D",
          "text": "D. Augmentation du risque d'AVC.",
          "correct": true
        },
        {
          "id": "E",
          "text": "E. Diminution du risque de thrombose.",
          "correct": false
        }
      ],
      "explanation": "Les Coxibs ont été associés à une augmentation du risque d'événements cardiovasculaires (infarctus, AVC)."
    },
    {
      "id": "q38",
      "type": "quiz",
      "difficulty": "difficile",
      "question": "L'augmentation du risque cardiovasculaire avec les Coxibs est probablement due à :",
      "options": [
        {
          "id": "A",
          "text": "A. Une inhibition excessive de la COX-1.",
          "correct": false
        },
        {
          "id": "B",
          "text": "B. Un déséquilibre de la balance TXA2/PGI2 en faveur d'un état pro-thrombotique.",
          "correct": true
        },
        {
          "id": "C",
          "text": "C. Une augmentation de la production de PGI2.",
          "correct": false
        },
        {
          "id": "D",
          "text": "D. Une diminution de la production de TXA2.",
          "correct": false
        },
        {
          "id": "E",
          "text": "E. Une stimulation de la vasodilatation.",
          "correct": false
        }
      ],
      "explanation": "L'augmentation du risque d'événements cardiovasculaires avec les Coxibs est probablement due à un déséquilibre de la balance TXA2/PGI2 en faveur d'un état pro-thrombotique."
    },
    {
      "id": "q39",
      "type": "quiz",
      "difficulty": "difficile",
      "question": "La biosynthèse des prostaglandines implique une cascade enzymatique. Quelles sont les étapes clés dans l'ordre ?",
      "options": [
        {
          "id": "A",
          "text": "A. Action des cyclooxygénases, libération de l'acide arachidonique, action des synthases spécifiques.",
          "correct": false
        },
        {
          "id": "B",
          "text": "B. Libération de l'acide arachidonique, action des cyclooxygénases, action des synthases spécifiques.",
          "correct": true
        },
        {
          "id": "C",
          "text": "C. Action des synthases spécifiques, libération de l'acide arachidonique, action des cyclooxygénases.",
          "correct": false
        },
        {
          "id": "D",
          "text": "D. Activation de la PGH2, action de la PLA2, action des COX.",
          "correct": false
        },
        {
          "id": "E",
          "text": "E. Libération de PGH2, action de la PLA2, action des synthases.",
          "correct": false
        }
      ],
      "explanation": "La synthèse des prostaglandines débute par la libération de l'acide arachidonique (Étape 1), suivie de l'action des cyclooxygénases (COX) (Étape 2), puis de l'action des synthases spécifiques (Étape 3)."
    },
    {
      "id": "q40",
      "type": "quiz",
      "difficulty": "difficile",
      "question": "Les rôles physiologiques des prostaglandines, principalement liés à la COX-1, incluent :",
      "options": [
        {
          "id": "A",
          "text": "A. La protection de la muqueuse gastrique.",
          "correct": true
        },
        {
          "id": "B",
          "text": "B. Le maintien de la fonction rénale.",
          "correct": true
        },
        {
          "id": "C",
          "text": "C. L'agrégation plaquettaire via le TXA2.",
          "correct": true
        },
        {
          "id": "D",
          "text": "D. La vasodilatation inflammatoire.",
          "correct": false
        },
        {
          "id": "E",
          "text": "E. La contraction utérine.",
          "correct": false
        }
      ],
      "explanation": "La COX-1 est une enzyme constitutive responsable des prostaglandines physiologiques, notamment la protection gastrique, la fonction rénale et la production de TXA2 par les plaquettes pour l'hémostase."
    },
    {
      "id": "q41",
      "type": "quiz",
      "difficulty": "difficile",
      "question": "Les prostaglandines produites par la COX-2 sont principalement impliquées dans :",
      "options": [
        {
          "id": "A",
          "text": "A. La protection gastrique.",
          "correct": false
        },
        {
          "id": "B",
          "text": "B. La fonction rénale de maintenance.",
          "correct": false
        },
        {
          "id": "C",
          "text": "C. L'inflammation.",
          "correct": true
        },
        {
          "id": "D",
          "text": "D. La douleur.",
          "correct": true
        },
        {
          "id": "E",
          "text": "E. La fièvre.",
          "correct": true
        }
      ],
      "explanation": "La COX-2 est inductible et produit les prostaglandines de l'inflammation, de la douleur et de la fièvre."
    },
    {
      "id": "q42",
      "type": "quiz",
      "difficulty": "difficile",
      "question": "L'effet thérapeutique anti-inflammatoire des AINS est justifié par :",
      "options": [
        {
          "id": "A",
          "text": "A. L'inhibition de la phospholipase A2.",
          "correct": false
        },
        {
          "id": "B",
          "text": "B. L'inhibition de la COX-1.",
          "correct": false
        },
        {
          "id": "C",
          "text": "C. L'inhibition de la COX-2.",
          "correct": true
        },
        {
          "id": "D",
          "text": "D. Le blocage de la production de prostaglandines de l'inflammation.",
          "correct": true
        },
        {
          "id": "E",
          "text": "E. La stimulation de la production de prostaglandines physiologiques.",
          "correct": false
        }
      ],
      "explanation": "L'effet thérapeutique anti-inflammatoire des AINS vient de l'inhibition de la COX-2, qui est responsable de la production des prostaglandines de l'inflammation."
    },
    {
      "id": "q43",
      "type": "quiz",
      "difficulty": "difficile",
      "question": "Les effets secondaires gastriques des AINS classiques sont expliqués par :",
      "options": [
        {
          "id": "A",
          "text": "A. L'inhibition de la COX-2.",
          "correct": false
        },
        {
          "id": "B",
          "text": "B. L'inhibition de la COX-1.",
          "correct": true
        },
        {
          "id": "C",
          "text": "C. La suppression de la protection de la muqueuse gastrique.",
          "correct": true
        },
        {
          "id": "D",
          "text": "D. La stimulation de la sécrétion d'acide gastrique.",
          "correct": false
        },
        {
          "id": "E",
          "text": "E. L'augmentation de la production de mucus.",
          "correct": false
        }
      ],
      "explanation": "Les effets secondaires fréquents des AINS classiques (toxicité gastrique) s'expliquent par l'inhibition concomitante et indésirable de la COX-1, entraînant une suppression de la protection de la muqueuse gastrique."
    },
    {
      "id": "q44",
      "type": "quiz",
      "difficulty": "difficile",
      "question": "Les effets secondaires rénaux des AINS classiques sont justifiés par :",
      "options": [
        {
          "id": "A",
          "text": "A. L'inhibition de la COX-2.",
          "correct": false
        },
        {
          "id": "B",
          "text": "B. L'inhibition de la COX-1.",
          "correct": true
        },
        {
          "id": "C",
          "text": "C. La vasodilatation de l'artériole afférente.",
          "correct": false
        },
        {
          "id": "D",
          "text": "D. La vasoconstriction de l'artériole afférente.",
          "correct": true
        },
        {
          "id": "E",
          "text": "E. Une insuffisance rénale aiguë fonctionnelle.",
          "correct": true
        }
      ],
      "explanation": "Les effets secondaires rénaux des AINS classiques s'expliquent par l'inhibition de la COX-1, qui entraîne une vasoconstriction de l'artériole afférente et peut provoquer une insuffisance rénale aiguë fonctionnelle."
    },
    {
      "id": "q45",
      "type": "quiz",
      "difficulty": "difficile",
      "question": "Comparez les AINS classiques et les Coxibs concernant leur inhibition des COX :",
      "options": [
        {
          "id": "A",
          "text": "A. Les AINS classiques inhibent sélectivement la COX-1.",
          "correct": false
        },
        {
          "id": "B",
          "text": "B. Les Coxibs inhibent préférentiellement la COX-2.",
          "correct": true
        },
        {
          "id": "C",
          "text": "C. Les AINS classiques inhibent à la fois la COX-1 et la COX-2.",
          "correct": true
        },
        {
          "id": "D",
          "text": "D. Les Coxibs épargnent la COX-1.",
          "correct": true
        },
        {
          "id": "E",
          "text": "E. Les AINS classiques n'ont pas d'effet sur la COX-1.",
          "correct": false
        }
      ],
      "explanation": "Les AINS classiques (non-sélectifs) inhibent à la fois la COX-1 et la COX-2. Les Coxibs (AINS sélectifs de la COX-2) inhibent préférentiellement la COX-2, en épargnant la COX-1."
    },
    {
      "id": "q46",
      "type": "quiz",
      "difficulty": "difficile",
      "question": "L'inhibition de la COX-1 par les AINS classiques peut entraîner :",
      "options": [
        {
          "id": "A",
          "text": "A. Une diminution de la protection gastrique.",
          "correct": true
        },
        {
          "id": "B",
          "text": "B. Une augmentation du risque d'ulcères et de saignements digestifs.",
          "correct": true
        },
        {
          "id": "C",
          "text": "C. Une vasoconstriction de l'artériole afférente rénale.",
          "correct": true
        },
        {
          "id": "D",
          "text": "D. Un effet anti-agrégant plaquettaire.",
          "correct": true
        },
        {
          "id": "E",
          "text": "E. Une diminution de la fièvre.",
          "correct": false
        }
      ],
      "explanation": "L'inhibition de la COX-1 est responsable de la plupart des effets secondaires des AINS classiques, incluant la toxicité gastrique (ulcères, saignements par suppression de la protection), la toxicité rénale (vasoconstriction de l'artériole afférente) et l'effet anti-agrégant (blocage de la production de TXA2)."
    },
    {
      "id": "q47",
      "type": "quiz",
      "difficulty": "difficile",
      "question": "L'inhibition de la COX-2 par les AINS classiques est responsable de :",
      "options": [
        {
          "id": "A",
          "text": "A. L'effet anti-inflammatoire.",
          "correct": true
        },
        {
          "id": "B",
          "text": "B. L'effet antalgique.",
          "correct": true
        },
        {
          "id": "C",
          "text": "C. L'effet antipyrétique.",
          "correct": true
        },
        {
          "id": "D",
          "text": "D. La toxicité gastrique.",
          "correct": false
        },
        {
          "id": "E",
          "text": "E. La toxicité rénale.",
          "correct": false
        }
      ],
      "explanation": "L'inhibition de la COX-2 est responsable des effets thérapeutiques des AINS classiques, qui sont anti-inflammatoires, antalgiques et antipyrétiques."
    },
    {
      "id": "q48",
      "type": "quiz",
      "difficulty": "difficile",
      "question": "La PGE2 joue des rôles variés dans l'organisme, notamment :",
      "options": [
        {
          "id": "A",
          "text": "A. Vasodilatation et augmentation de la perméabilité vasculaire dans l'inflammation.",
          "correct": true
        },
        {
          "id": "B",
          "text": "B. Sensibilisation des terminaisons nerveuses nociceptives.",
          "correct": true
        },
        {
          "id": "C",
          "text": "C. Élévation du 'point de consigne' de la température corporelle dans l'hypothalamus.",
          "correct": true
        },
        {
          "id": "D",
          "text": "D. Contraction du myomètre.",
          "correct": true
        },
        {
          "id": "E",
          "text": "E. Agrégation plaquettaire.",
          "correct": false
        }
      ],
      "explanation": "La PGE2 est un puissant vasodilatateur et augmente la perméabilité vasculaire dans l'inflammation, sensibilise les terminaisons nerveuses nociceptives à la douleur, élève le 'point de consigne' de la température corporelle dans l'hypothalamus (fièvre) et provoque la contraction du myomètre."
    },
    {
      "id": "q49",
      "type": "quiz",
      "difficulty": "difficile",
      "question": "La PGI2 (Prostacycline) est impliquée dans :",
      "options": [
        {
          "id": "A",
          "text": "A. La vasodilatation inflammatoire.",
          "correct": true
        },
        {
          "id": "B",
          "text": "B. L'augmentation de la perméabilité vasculaire inflammatoire.",
          "correct": true
        },
        {
          "id": "C",
          "text": "C. L'anti-agrégation plaquettaire.",
          "correct": true
        },
        {
          "id": "D",
          "text": "D. La vasoconstriction.",
          "correct": false
        },
        {
          "id": "E",
          "text": "E. La production par les plaquettes.",
          "correct": false
        }
      ],
      "explanation": "La PGI2 est un puissant vasodilatateur et augmente la perméabilité vasculaire dans l'inflammation. Elle est également un puissant anti-agrégant plaquettaire et vasodilatateur dans l'hémostase, produite par les cellules endothéliales."
    },
    {
      "id": "q50",
      "type": "quiz",
      "difficulty": "difficile",
      "question": "Les prostaglandines, en tant que médiateurs lipidiques locaux, présentent les caractéristiques suivantes :",
      "options": [
        {
          "id": "A",
          "text": "A. Elles sont stockées en grande quantité dans les cellules.",
          "correct": false
        },
        {
          "id": "B",
          "text": "B. Elles sont synthétisées à la demande en réponse à divers stimuli.",
          "correct": true
        },
        {
          "id": "C",
          "text": "C. Elles agissent de manière autocrine ou paracrine.",
          "correct": true
        },
        {
          "id": "D",
          "text": "D. Elles ont une demi-vie très courte.",
          "correct": true
        },
        {
          "id": "E",
          "text": "E. Leurs effets biologiques sont toujours les mêmes quel que soit le type de prostaglandine.",
          "correct": false
        }
      ],
      "explanation": "Les prostaglandines ne sont pas stockées mais sont synthétisées à la demande, agissent de manière autocrine ou paracrine, et ont une demi-vie très courte. Leurs effets biologiques sont extrêmement variés et parfois opposés selon le type de prostaglandine et le récepteur."
    }
  ]
}